ripozo_tests
