Metadata-Version: 1.1
Name: ripozo-tests
Version: 0.1.15
Summary: A helper package for creating tests for ripozo and its extensions
Home-page: UNKNOWN
Author: Tim Martin
Author-email: tim.martin@vertical-knowledge.com
License: UNKNOWN
Platform: UNKNOWN
Classifier: Development Status :: 3 - Alpha
Classifier: Operating System :: OS Independent
Classifier: Programming Language :: Python
Classifier: Programming Language :: Python :: 2
Classifier: Programming Language :: Python :: 2.6
Classifier: Programming Language :: Python :: 2.7
Classifier: Programming Language :: Python :: 3
Classifier: Programming Language :: Python :: 3.4
